design.sv
// Code your design here

module up_down_counter (
    input clk,
    input rst,
    input up_down,
    input enable,
    output reg [3:0] count
);
    always @(posedge clk or posedge rst) begin
        if (rst)
            count <= 4'b0;
        else if (enable) begin
            if (up_down)
                count <= count + 1;
            else
                count <= count - 1;
        end
    end
endmodule

testbench.sv
// Code your testbench here
// or browse Examples
​
module tb;
    reg clk = 0, rst = 1, up_down, enable;
    wire [3:0] count;
​
    up_down_counter dut (.*);
​
    always #5 clk = ~clk;
​
    // === MANUAL COVERAGE: Use reg arrays (Icarus-safe) ===
    reg [15:0] count_covered;
    reg [3:0] en_dir_covered;
​
    // Sample on clock
    always @(posedge clk) begin
        if (!rst) begin
            count_covered[count] = 1'b1;
            en_dir_covered[{enable, up_down}] = 1'b1;
        end
    end
​
    initial begin
        count_covered = 16'b0;
        en_dir_covered = 4'b0;
​
        $display("=== Up/Down Counter Test with Manual Coverage ===");
        rst = 1;
        #15 rst = 0;
​
        repeat(100) begin
            enable  = $random % 2;
            up_down = $random % 2;
            #10;
        end
​
        #20;
        $display("Final count = %0d", count);
​
        // === COVERAGE REPORT ===
        begin : coverage_report
            integer i, covered_count, covered_combos;
            covered_count = 0;
            covered_combos = 0;
​
            for (i = 0; i < 16; i = i + 1)
                if (count_covered[i]) covered_count = covered_count + 1;
​
            for (i = 0; i < 4; i = i + 1)
                if (en_dir_covered[i]) covered_combos = covered_combos + 1;
​
            $display("Count Coverage: %0d/16 (%.2f%%)", 
                     covered_count, (covered_count * 100.0)/16);
            $display("Enable+Dir Coverage: %0d/4 (%.2f%%)", 
                     covered_combos, (covered_combos * 100.0)/4);
            $display("Total Functional Coverage: %.2f%%", 
                     ((covered_count * 100.0)/16 + (covered_combos * 100.0)/4)/2);
        end : coverage_report
​
        $finish;
    end
​
    initial 
        $monitor("t=%0t | rst=%b en=%b dir=%b | count=%0d", 
                 $time, rst, enable, up_down, count);
endmodule

counter.vcd
$date
	Thu Nov 20 12:53:11 2025
$end
$version
	Icarus Verilog
$end
$timescale
	1s
$end
$scope module tb $end
$var wire 4 ! count [3:0] $end
$var reg 1 " clk $end
$var reg 16 # count_covered [15:0] $end
$var reg 4 $ en_dir_covered [3:0] $end
$var reg 1 % enable $end
$var reg 1 & rst $end
$var reg 1 ' up_down $end
$scope module dut $end
$var wire 1 " clk $end
$var wire 1 % enable $end
$var wire 1 & rst $end
$var wire 1 ' up_down $end
$var reg 4 ( count [3:0] $end
$upscope $end
$scope begin coverage_report $end
$var integer 32 ) covered_combos [31:0] $end
$var integer 32 * covered_count [31:0] $end
$var integer 32 + i [31:0] $end
$upscope $end
$upscope $end
$enddefinitions $end
$comment Show the parameter values. $end
$dumpall
$end
#0
$dumpvars
bx +
bx *
bx )
bx (
x'
1&
x%
b0 $
b0 #
0"
bx !
$end
#5
b0 !
b0 (
1"
#10
0"
#15
b10 $
b1 #
1"
1'
0%
0&
#20
0"
#25
b1 !
b1 (
b1010 $
1"
1%
#30
0"
#35
b10 !
b10 (
b11 #
1"
#40
0"
#45
b1 !
b1 (
b1110 $
b111 #
1"
0'
#50
0"
#55
b10 !
b10 (
1"
1'
#60
0"
#65
1"
0%
#70
0"
#75
b1 !
b1 (
1"
0'
1%
#80
0"
#85
b0 !
b0 (
1"
#90
0"
#95
b1111 !
b1111 (
1"
#100
0"
#105
b0 !
b0 (
b1000000000000111 #
1"
1'
#110
0"
#115
1"
0%
#120
0"
#125
b1111 $
1"
0'
#130
0"
#135
1"
1'
#140
0"
#145
1"
#150
0"
#155
b1 !
b1 (
1"
1%
#160
0"
#165
b0 !
b0 (
1"
0'
#170
0"
#175
1"
0%
#180
0"
#185
1"
1'
#190
0"
#195
1"
#200
0"
#205
b1 !
b1 (
1"
1%
#210
0"
#215
b10 !
b10 (
1"
#220
0"
#225
1"
0'
0%
#230
0"
#235
b11 !
b11 (
1"
1'
1%
#240
0"
#245
b10 !
b10 (
b1000000000001111 #
1"
0'
#250
0"
#255
1"
0%
#260
0"
#265
1"
#270
0"
#275
b1 !
b1 (
1"
1%
#280
0"
#285
1"
1'
0%
#290
0"
#295
b0 !
b0 (
1"
0'
1%
#300
0"
#305
1"
0%
#310
0"
#315
1"
#320
0"
#325
b1 !
b1 (
1"
1'
1%
#330
0"
#335
b10 !
b10 (
1"
#340
0"
#345
b1 !
b1 (
1"
0'
#350
0"
#355
1"
1'
0%
#360
0"
#365
b10 !
b10 (
1"
1%
#370
0"
#375
1"
0'
0%
#380
0"
#385
b11 !
b11 (
1"
1'
1%
#390
0"
#395
1"
0%
#400
0"
#405
b10 !
b10 (
1"
0'
1%
#410
0"
#415
b11 !
b11 (
1"
1'
#420
0"
#425
b10 !
b10 (
1"
0'
#430
0"
#435
b11 !
b11 (
1"
1'
#440
0"
#445
1"
0'
0%
#450
0"
#455
1"
#460
0"
#465
b100 !
b100 (
1"
1'
1%
#470
0"
#475
b1000000000011111 #
1"
0'
0%
#480
0"
#485
b101 !
b101 (
1"
1'
1%
#490
0"
#495
b110 !
b110 (
b1000000000111111 #
1"
#500
0"
#505
b101 !
b101 (
b1000000001111111 #
1"
0'
#510
0"
#515
b110 !
b110 (
1"
1'
#520
0"
#525
b101 !
b101 (
1"
0'
#530
0"
#535
1"
0%
#540
0"
#545
1"
#550
0"
#555
1"
#560
0"
#565
b110 !
b110 (
1"
1'
1%
#570
0"
#575
b111 !
b111 (
1"
#580
0"
#585
b110 !
b110 (
b1000000011111111 #
1"
0'
#590
0"
#595
b111 !
b111 (
1"
1'
#600
0"
#605
1"
0'
0%
#610
0"
#615
b1000 !
b1000 (
1"
1'
1%
#620
0"
#625
b1000000111111111 #
1"
0%
#630
0"
#635
b1001 !
b1001 (
1"
1%
#640
0"
#645
b1000 !
b1000 (
b1000001111111111 #
1"
0'
#650
0"
#655
1"
0%
#660
0"
#665
b111 !
b111 (
1"
1%
#670
0"
#675
1"
0%
#680
0"
#685
b1000 !
b1000 (
1"
1'
1%
#690
0"
#695
1"
0'
0%
#700
0"
#705
b111 !
b111 (
1"
1%
#710
0"
#715
1"
0%
#720
0"
#725
b110 !
b110 (
1"
1%
#730
0"
#735
1"
1'
0%
#740
0"
#745
1"
#750
0"
#755
b111 !
b111 (
1"
1%
#760
0"
#765
b1000 !
b1000 (
1"
#770
0"
#775
1"
0'
0%
#780
0"
#785
1"
1'
#790
0"
#795
1"
0'
#800
0"
#805
b1001 !
b1001 (
1"
1'
1%
#810
0"
#815
1"
0'
0%
#820
0"
#825
1"
1'
#830
0"
#835
b1000 !
b1000 (
1"
0'
1%
#840
0"
#845
1"
0%
#850
0"
#855
b1001 !
b1001 (
1"
1'
1%
#860
0"
#865
1"
0'
0%
#870
0"
#875
1"
1'
#880
0"
#885
1"
0'
#890
0"
#895
b1000 !
b1000 (
1"
1%
#900
0"
#905
1"
0%
#910
0"
#915
b111 !
b111 (
1"
1%
#920
0"
#925
b1000 !
b1000 (
1"
1'
#930
0"
#935
1"
0'
0%
#940
0"
#945
1"
#950
0"
#955
b111 !
b111 (
1"
1%
#960
0"
#965
1"
0%
#970
0"
#975
1"
1'
#980
0"
#985
b1000 !
b1000 (
1"
1%
#990
0"
#995
1"
0%
#1000
0"
#1005
b1001 !
b1001 (
1"
1%
#1010
0"
#1015
b1010 !
b1010 (
1"
#1020
0"
#1025
b1011 !
b1011 (
b1000011111111111 #
1"
#1030
0"
#1035
b1100 !
b1100 (
b1000111111111111 #
1"
b100 +
b100 )
b1100 *
